sentinelpy/__init__.py
sentinelpy/exceptions.py
sentinelpy/main.py
sentinelpy/query_sentinel_products_response.py
sentinelpy/request/__init__.py
sentinelpy/request/model.py
sentinelpy/request/request_query_builder.py
sentinelpy/request/sentinel_product_request_builder.py
sentinelpy/request/validate_query_builder_args.py
sentinelpy/request/value_formatters.py
sentinelpy-0.1.0.dist-info/LICENSE
sentinelpy-0.1.0.dist-info/WHEEL
sentinelpy-0.1.0.dist-info/METADATA
sentinelpy-0.1.0.dist-info/RECORD
