Metadata-Version: 2.1
Name: sentinelpy
Version: 0.1.0
Summary: Queries ESA Sentinel APIs for products
Home-page: https://github.com/UKHO/sentinelpy
License: MIT
Keywords: SentinelHub,Copernicus Open Access Hub
Author: UK Hydrographic Office
Author-email: datascienceandengineering@ukho.gov.uk
Requires-Python: >=3.6,<4.0
Classifier: Development Status :: 3 - Alpha
Classifier: Intended Audience :: Developers
Classifier: Intended Audience :: Science/Research
Classifier: License :: OSI Approved :: MIT License
Classifier: Natural Language :: English
Classifier: Programming Language :: Python :: 3
Classifier: Programming Language :: Python :: 3.6
Classifier: Programming Language :: Python :: 3.7
Classifier: Programming Language :: Python :: 3.8
Classifier: Topic :: Scientific/Engineering :: GIS
Classifier: Typing :: Typed
Requires-Dist: requests (>=2.25.0,<3.0.0)
Project-URL: Bug Tracker, https://github.com/UKHO/sentinelpy/issues
Project-URL: Repository, https://github.com/UKHO/sentinelpy
